[
    {"esp": "el faro"},
    {"esp": "septentrional"},
    {"esp": "el castillo de arena"},
    {"esp": "alquilar"},
    {"esp": "el columpio"},
    {"esp": "la ocupación"},
    {"esp": "interesar"},
    {"esp": "el guijarro"},
    {"esp": "señor/señora"},
    {"esp": "el pastizal"},
    {"esp": "la primavera"},
    {"esp": "los poderes"},
    {"esp": "el lugareño/la lugareña"},
    {"esp": "de antemano"},
    {"esp": "descalzo/descalza"},
    {"esp": "chapotear"},
    {"esp": "el hormigueo"},
    {"esp": "embarcar"},
    {"esp": "poder"},
    {"esp": "sediento/sedienta"},
    {"esp": "lugareño/lugareña"},
    {"esp": "dibujar"},
    {"esp": "fructífero/fructífera"},
    {"esp": "el tesauro"},
    {"esp": "el Señor"},
    {"esp": "llegar"},
    {"esp": "mueble"}
]